[{"videoID": "aXeqQAobiaI"}, {"segInfo": [[0, 31], [31, 56], [56, 90], [90, 138], [138, 243], [243, 282]]}, {"ID": "aXeqQAobiaI_Q0", "Question": "How to open and close <the motion detector>?", "Reason": "", "QueryType": "Text Only", "Segment": [1], "Filename": "aXeqQAobiaI_img_Q0.jpg", "Start_EndTime": [[0, 31]]}, {"ID": "aXeqQAobiaI_Q1", "Question": "What is <bbox/the white plastic piece> inside the motion detector?", "Reason": "", "QueryType": "Text and Video", "Segment": [2], "Filename": "aXeqQAobiaI_bbox_Q1.jpg", "Start_EndTime": [[44, 50]]}, {"ID": "aXeqQAobiaI_Q2", "Question": "How to change battery for the <motion detector>?", "Reason": "", "QueryType": "Text Only", "Segment": [3], "Filename": "aXeqQAobiaI_img_Q2.jpg", "Start_EndTime": [[56, 90]]}, {"ID": "aXeqQAobiaI_Q3", "Question": "How to attach the motion detector on <the flat surface bracket>?", "Reason": "", "QueryType": "Text and Video", "Segment": [4], "Filename": "aXeqQAobiaI_img_Q3.jpg", "Start_EndTime": [[95, 137]]}, {"ID": "aXeqQAobiaI_Q4", "Question": "How to attach the motion detector on <bbox/the corner surface bracket>?", "Reason": "", "QueryType": "Text and Video", "Segment": [5], "Filename": "aXeqQAobiaI_bbox_Q4.jpg", "Start_EndTime": [[143, 242]]}, {"ID": "aXeqQAobiaI_Q5", "Question": "How to remove the <motion detector>?", "Reason": "", "QueryType": "Text Only", "Segment": [6], "Filename": "aXeqQAobiaI_img_Q5.jpg", "Start_EndTime": [[243, 282]]}]