[{"videoID": "c4EYWCA4CBY"}, {"segInfo": [[0, 45], [45, 196], [196, 342], [342, 427], [427, 524], [524, 643], [643, 792]]}, {"ID": "c4EYWCA4CBY_Q0", "Question": "What is <bbox/that> for on the nest hub?", "QueryType": "Video Only", "Segment": [1, 4], "Filename": "c4EYWCA4CBY_bbox_Q0.jpg", "Start_EndTime": [[28, 45], [343, 371]]}, {"ID": "c4EYWCA4CBY_Q1", "Question": "What is the function of <bbox/that> on the nest hub?", "QueryType": "Video Only", "Segment": [1, 4], "Filename": "c4EYWCA4CBY_bbox_Q0.jpg", "Start_EndTime": [[28, 45], [343, 371]]}, {"ID": "c4EYWCA4CBY_Q2", "Question": "Does <bbox/that> on the nest hub have any function?", "QueryType": "Video Only", "Segment": [1, 4], "Filename": "c4EYWCA4CBY_bbox_Q0.jpg", "Start_EndTime": [[28, 45], [343, 371]]}, {"ID": "c4EYWCA4CBY_Q3", "Question": "How does the sleep tracking work on <the nest hub>?", "QueryType": "Text Only", "Segment": [2], "Filename": "c4EYWCA4CBY_img_Q1.jpg", "Start_EndTime": [[46, 196]]}, {"ID": "c4EYWCA4CBY_Q4", "Question": "How can I track my sleep with <the nest hub>?", "QueryType": "Text Only", "Segment": [2], "Filename": "c4EYWCA4CBY_img_Q1.jpg", "Start_EndTime": [[46, 196]]}, {"ID": "c4EYWCA4CBY_Q5", "Question": "Could I track my sleep with <the nest hub>?", "QueryType": "Text Only", "Segment": [2], "Filename": "c4EYWCA4CBY_img_Q1.jpg", "Start_EndTime": [[46, 196]]}, {"ID": "c4EYWCA4CBY_Q6", "Question": "How to set the alarm on <the nest hub>?", "QueryType": "Text Only", "Segment": [3], "Filename": "c4EYWCA4CBY_img_Q2.jpg", "Start_EndTime": [[199, 342]]}, {"ID": "c4EYWCA4CBY_Q7", "Question": "Where can I set the alarm on <the nest hub>?", "QueryType": "Text Only", "Segment": [3], "Filename": "c4EYWCA4CBY_img_Q2.jpg", "Start_EndTime": [[199, 342]]}, {"ID": "c4EYWCA4CBY_Q8", "Question": "I would like to set an alarm on <the next hub>, what should I do?", "QueryType": "Text Only", "Segment": [3], "Filename": "c4EYWCA4CBY_img_Q2.jpg", "Start_EndTime": [[199, 342]]}, {"ID": "c4EYWCA4CBY_Q9", "Question": "How to customize the alarm snoozing on <the nest hub>?", "QueryType": "Text Only", "Segment": [3], "Filename": "c4EYWCA4CBY_img_Q3.jpg", "Start_EndTime": [[280, 287]]}, {"ID": "c4EYWCA4CBY_Q10", "Question": "Does <the nest hub> support alarm snoozing customization?", "QueryType": "Text Only", "Segment": [3], "Filename": "c4EYWCA4CBY_img_Q3.jpg", "Start_EndTime": [[280, 287]]}, {"ID": "c4EYWCA4CBY_Q11", "Question": "Where can I customize the alarm snoozing on <the next hub>?", "QueryType": "Text Only", "Segment": [3], "Filename": "c4EYWCA4CBY_img_Q3.jpg", "Start_EndTime": [[280, 287]]}, {"ID": "c4EYWCA4CBY_Q12", "Question": "Would the alarm continue if <the nest hub> break down the connection to Wi-Fi?", "QueryType": "Text Only", "Segment": [3], "Filename": "c4EYWCA4CBY_img_Q4.jpg", "Start_EndTime": [[286, 302]]}, {"ID": "c4EYWCA4CBY_Q13", "Question": "What would happen to the alarm if <the nest hub> disconnected with Wi-Fi?", "QueryType": "Text Only", "Segment": [3], "Filename": "c4EYWCA4CBY_img_Q4.jpg", "Start_EndTime": [[286, 302]]}, {"ID": "c4EYWCA4CBY_Q14", "Question": "Does the alarm function of <the nest hub> rely on Wi-Fi connection?", "QueryType": "Text Only", "Segment": [3], "Filename": "c4EYWCA4CBY_img_Q4.jpg", "Start_EndTime": [[286, 302]]}, {"ID": "c4EYWCA4CBY_Q15", "Question": "Could <the nest hub> provide specific ambient sound to help to sleep?", "QueryType": "Text Only", "Segment": [3], "Filename": "c4EYWCA4CBY_img_Q5.jpg", "Start_EndTime": [[302, 318]]}, {"ID": "c4EYWCA4CBY_Q16", "Question": "I want to customize the ambient sound of <the nest hub> to get sleeping, how to do that?", "QueryType": "Text Only", "Segment": [3], "Filename": "c4EYWCA4CBY_img_Q5.jpg", "Start_EndTime": [[302, 318]]}, {"ID": "c4EYWCA4CBY_Q17", "Question": "Where can I set an ambient sound for sleeping on <the nest hub>?", "QueryType": "Text Only", "Segment": [3], "Filename": "c4EYWCA4CBY_img_Q5.jpg", "Start_EndTime": [[302, 318]]}, {"ID": "c4EYWCA4CBY_Q18", "Question": "How does the speaker of <the nest hub> perform?", "QueryType": "Text Only", "Segment": [4], "Filename": "c4EYWCA4CBY_img_Q6.jpg", "Start_EndTime": [[393, 427]]}, {"ID": "c4EYWCA4CBY_Q19", "Question": "Does the speaker of  <the nest hub> sound terrible?", "QueryType": "Text Only", "Segment": [4], "Filename": "c4EYWCA4CBY_img_Q6.jpg", "Start_EndTime": [[393, 427]]}, {"ID": "c4EYWCA4CBY_Q20", "Question": "Do I need to concern about the speaker performance of <the test hub>?", "QueryType": "Text Only", "Segment": [4], "Filename": "c4EYWCA4CBY_img_Q6.jpg", "Start_EndTime": [[393, 427]]}, {"ID": "c4EYWCA4CBY_Q21", "Question": "How to set up <the nest hub>?", "QueryType": "Text Only", "Segment": [5], "Filename": "c4EYWCA4CBY_img_Q7.jpg", "Start_EndTime": [[447, 461]]}, {"ID": "c4EYWCA4CBY_Q22", "Question": "Is it complicate to set up <the nest hub>?", "QueryType": "Text Only", "Segment": [5], "Filename": "c4EYWCA4CBY_img_Q7.jpg", "Start_EndTime": [[447, 461]]}, {"ID": "c4EYWCA4CBY_Q23", "Question": "Does it take much effort to set up <the nest hub>?", "QueryType": "Text Only", "Segment": [5], "Filename": "c4EYWCA4CBY_img_Q7.jpg", "Start_EndTime": [[447, 461]]}, {"ID": "c4EYWCA4CBY_Q24", "Question": "Could <the nest hub> work as photo frame?", "QueryType": "Text Only", "Segment": [5], "Filename": "c4EYWCA4CBY_img_Q8.jpg", "Start_EndTime": [[469, 518]]}, {"ID": "c4EYWCA4CBY_Q25", "Question": "Can I use <the nest hub> as photo frame?", "QueryType": "Text Only", "Segment": [5], "Filename": "c4EYWCA4CBY_img_Q8.jpg", "Start_EndTime": [[469, 518]]}, {"ID": "c4EYWCA4CBY_Q26", "Question": "What should I set so <the nest hub> works like a photo frame?", "QueryType": "Text Only", "Segment": [5], "Filename": "c4EYWCA4CBY_img_Q8.jpg", "Start_EndTime": [[469, 518]]}, {"ID": "c4EYWCA4CBY_Q27", "Question": "Could I use <the nest hub> as a dynamic weather clock?", "QueryType": "Text Only", "Segment": [5], "Filename": "c4EYWCA4CBY_img_Q9.jpg", "Start_EndTime": [[518, 524]]}, {"ID": "c4EYWCA4CBY_Q28", "Question": "How to set <the nest hub> so it works as a dynamic weather clock?", "QueryType": "Text Only", "Segment": [5], "Filename": "c4EYWCA4CBY_img_Q9.jpg", "Start_EndTime": [[518, 524]]}, {"ID": "c4EYWCA4CBY_Q29", "Question": "What should I do with <the nest hub> to render it a dynamic weather clock?", "QueryType": "Text Only", "Segment": [5], "Filename": "c4EYWCA4CBY_img_Q9.jpg", "Start_EndTime": [[518, 524]]}, {"ID": "c4EYWCA4CBY_Q30", "Question": "Can I use <the nest hub> to control my smart home?", "QueryType": "Text Only", "Segment": [6], "Filename": "c4EYWCA4CBY_img_Q10.jpg", "Start_EndTime": [[525, 564]]}, {"ID": "c4EYWCA4CBY_Q31", "Question": "How to use <the nest hub> with my smart home?", "QueryType": "Text Only", "Segment": [6], "Filename": "c4EYWCA4CBY_img_Q10.jpg", "Start_EndTime": [[525, 564]]}, {"ID": "c4EYWCA4CBY_Q32", "Question": "Could <the nest hub> cooperate well with my smart home?", "QueryType": "Text Only", "Segment": [6], "Filename": "c4EYWCA4CBY_img_Q10.jpg", "Start_EndTime": [[525, 564]]}, {"ID": "c4EYWCA4CBY_Q33", "Question": "Could <the nest hub> control music playing?", "QueryType": "Text Only", "Segment": [6], "Filename": "c4EYWCA4CBY_img_Q11.jpg", "Start_EndTime": [[565, 593]]}, {"ID": "c4EYWCA4CBY_Q34", "Question": "How to control music playing using <the nest hub>?", "QueryType": "Text Only", "Segment": [6], "Filename": "c4EYWCA4CBY_img_Q11.jpg", "Start_EndTime": [[565, 593]]}, {"ID": "c4EYWCA4CBY_Q35", "Question": "Does <the nest hub> support music playing control?", "QueryType": "Text Only", "Segment": [6], "Filename": "c4EYWCA4CBY_img_Q11.jpg", "Start_EndTime": [[565, 593]]}, {"ID": "c4EYWCA4CBY_Q36", "Question": "How to use the Google assistant with <the nest hub>?", "QueryType": "Text Only", "Segment": [7], "Filename": "c4EYWCA4CBY_img_Q12.jpg", "Start_EndTime": [[643, 790]]}, {"ID": "c4EYWCA4CBY_Q37", "Question": "What should I do to use the Google assistant with <the nest hub>?", "QueryType": "Text Only", "Segment": [7], "Filename": "c4EYWCA4CBY_img_Q12.jpg", "Start_EndTime": [[643, 790]]}, {"ID": "c4EYWCA4CBY_Q38", "Question": "Does <the nest hub> provide Google assistant service?", "QueryType": "Text Only", "Segment": [7], "Filename": "c4EYWCA4CBY_img_Q12.jpg", "Start_EndTime": [[643, 790]]}, {"ID": "c4EYWCA4CBY_Q39", "Question": "How could <the nest hub> help me to cook?", "QueryType": "Text Only", "Segment": [7], "Filename": "c4EYWCA4CBY_img_Q13.jpg", "Start_EndTime": [[693, 765]]}, {"ID": "c4EYWCA4CBY_Q40", "Question": "Can I find recipe and shopping list on <the nest hub>?", "QueryType": "Text Only", "Segment": [7], "Filename": "c4EYWCA4CBY_img_Q13.jpg", "Start_EndTime": [[693, 765]]}, {"ID": "c4EYWCA4CBY_Q41", "Question": "Does <the nest hub> work well in kitchen?", "QueryType": "Text Only", "Segment": [7], "Filename": "c4EYWCA4CBY_img_Q13.jpg", "Start_EndTime": [[693, 765]]}, {"ID": "c4EYWCA4CBY_Q42", "Question": "What does the reminder function of <the nest hub> do?", "QueryType": "Text Only", "Segment": [7], "Filename": "c4EYWCA4CBY_img_Q14.jpg", "Start_EndTime": [[765, 792]]}, {"ID": "c4EYWCA4CBY_Q43", "Question": "How can I use <the nest hub> as reminder?", "QueryType": "Text Only", "Segment": [7], "Filename": "c4EYWCA4CBY_img_Q14.jpg", "Start_EndTime": [[765, 792]]}, {"ID": "c4EYWCA4CBY_Q44", "Question": "Does <the nest hub> provide reminder function?", "QueryType": "Text Only", "Segment": [7], "Filename": "c4EYWCA4CBY_img_Q14.jpg", "Start_EndTime": [[765, 792]]}]