[{"videoID": "FScOiYMzFC8"}, {"segInfo": [[0, 89], [89, 191], [191, 254], [254, 315], [315, 389], [389, 495], [495, 574]]}, {"ID": "FScOiYMzFC8_Q0", "Question": "What's the brightness of this <light>?", "Reason": "text: \u201cthe brightness scale ...\u201d", "QueryType": "Text Only", "Segment": [1], "Filename": "FScOiYMzFC8_img_Q0.jpg", "Start_EndTime": [[48, 54]]}, {"ID": "FScOiYMzFC8_Q1", "Question": "What is the function of <bbox/it>?", "Reason": "image info", "QueryType": "Text and Video", "Segment": [1], "Filename": "FScOiYMzFC8_bbox_Q1.jpg", "Start_EndTime": [[56, 68]]}, {"ID": "FScOiYMzFC8_Q2", "Question": "How to charge the <light>?", "Reason": "text: \u201crechargeable ...\u201d", "QueryType": "Text Only", "Segment": [1], "Filename": "FScOiYMzFC8_img_Q2.jpg", "Start_EndTime": [[72, 89]]}, {"ID": "FScOiYMzFC8_Q3", "Question": "What is the function of <bbox/it>?", "Reason": "image info", "QueryType": "Text and Video", "Segment": [2], "Filename": "FScOiYMzFC8_bbox_Q3.jpg", "Start_EndTime": [[90, 96]]}, {"ID": "FScOiYMzFC8_Q4", "Question": "How to tighten the <bbox/it>?", "Reason": "image info", "QueryType": "Text and Video", "Segment": [2], "Filename": "FScOiYMzFC8_bbox_Q4.jpg", "Start_EndTime": [[98, 111]]}, {"ID": "FScOiYMzFC8_Q5", "Question": "What is the function of <bbox/it>?", "Reason": "image info", "QueryType": "Text and Video", "Segment": [2], "Filename": "FScOiYMzFC8_bbox_Q5.jpg", "Start_EndTime": [[122, 138]]}, {"ID": "FScOiYMzFC8_Q6", "Question": "How to connect <bbox/it> to my bike?", "Reason": "image info", "QueryType": "Text and Video", "Segment": [2], "Filename": "FScOiYMzFC8_bbox_Q6.jpg", "Start_EndTime": [[145, 160]]}, {"ID": "FScOiYMzFC8_Q7", "Question": "How to connect <bbox/it> to the light?", "Reason": "image info", "QueryType": "Text and Video", "Segment": [2], "Filename": "FScOiYMzFC8_bbox_Q7.jpg", "Start_EndTime": [[175, 182]]}, {"ID": "FScOiYMzFC8_Q8", "Question": "How to change the mode of <light>?", "Reason": "text: \u201cmode ...\u201d", "QueryType": "Text Only", "Segment": [3], "Filename": "FScOiYMzFC8_img_Q8.jpg", "Start_EndTime": [[205, 214]]}, {"ID": "FScOiYMzFC8_Q9", "Question": "How to open the <bbox/it>?", "Reason": "image info", "QueryType": "Text and Video", "Segment": [4], "Filename": "FScOiYMzFC8_bbox_Q9.jpg", "Start_EndTime": [[255, 258]]}, {"ID": "FScOiYMzFC8_Q10", "Question": "How to change the mode of <bbox/it>?", "Reason": "image info", "QueryType": "Text and Video", "Segment": [4], "Filename": "FScOiYMzFC8_bbox_Q10.jpg", "Start_EndTime": [[261, 273]]}, {"ID": "FScOiYMzFC8_Q11", "Question": "How to close the <bbox/it>?", "Reason": "image info", "QueryType": "Text and Video", "Segment": [4], "Filename": "FScOiYMzFC8_bbox_Q11.jpg", "Start_EndTime": [[312, 314]]}]