[{"videoID": "y5gakyb7hGo"}, {"segInfo": [[0, 39], [39, 114], [114, 165], [165, 209], [209, 259]]}, {"ID": "y5gakyb7hGo_Q0", "Question": "How to assemble <bbox/this part>?", "QueryType": "Text and Video", "Segment": [1], "Filename": "y5gakyb7hGo_bbox_Q0.jpg", "Start_EndTime": [[25, 31]]}, {"ID": "y5gakyb7hGo_Q1", "Question": "How to install the blade of the <blender>?", "QueryType": "Text Only", "Segment": [2], "Filename": "y5gakyb7hGo_img_Q1.jpg", "Start_EndTime": [[72, 79]]}, {"ID": "y5gakyb7hGo_Q2", "Question": "How to install <bbox/this part>?", "QueryType": "Video Only", "Segment": [2], "Filename": "y5gakyb7hGo_bbox_Q2.jpg", "Start_EndTime": [[96, 112]]}, {"ID": "y5gakyb7hGo_Q3", "Question": "What is <bbox/this part> for?", "QueryType": "Video Only", "Segment": [3], "Filename": "y5gakyb7hGo_bbox_Q3.jpg", "Start_EndTime": [[158, 162]]}]